rotate_group_words/__init__.py
rotate_group_words/entry.py
rotate_group_words/rotate_group_words.py
rotate_group_words-0.4.6.dist-info/METADATA
rotate_group_words-0.4.6.dist-info/WHEEL
rotate_group_words-0.4.6.dist-info/entry_points.txt
rotate_group_words-0.4.6.dist-info/RECORD
