Metadata-Version: 2.3
Name: rotate_group_words
Version: 0.4.6
Summary: 
Author: TSX
Author-email: miladtsx@gmail.com
Requires-Python: >=3.13
Classifier: Programming Language :: Python :: 3
Classifier: Programming Language :: Python :: 3.13
Project-URL: Homepage, https://github.com/miladtsx/pyractice_array
Project-URL: Issues, https://github.com/miladtsx/pyractice_array/issues
